RetryDecorator/__init__.py
retry_decorator_mt-1.0.1.dist-info/licenses/LICENSE
retry_decorator_mt-1.0.1.dist-info/METADATA
retry_decorator_mt-1.0.1.dist-info/WHEEL
retry_decorator_mt-1.0.1.dist-info/top_level.txt
retry_decorator_mt-1.0.1.dist-info/RECORD
