Metadata-Version: 2.4
Name: retry-decorator-mt
Version: 1.0.1
Summary: Decorator to allow for retry of th decorated object if a given exception is raised
Author-email: Vincent Martel <vincent.martel.11235@gmail.com>
License: MIT
Keywords: decorator,utilities,retry,error handling,timeout,error,quality of life
Classifier: Development Status :: 5 - Production/Stable
Classifier: Intended Audience :: Developers
Classifier: Programming Language :: Python :: 3
Classifier: Programming Language :: Python :: 3.9
Classifier: Programming Language :: Python :: 3.10
Classifier: Programming Language :: Python :: 3.11
Classifier: Programming Language :: Python :: 3.12
Requires-Python: >=3.9
License-File: LICENSE
Dynamic: description
Dynamic: description-content-type
Dynamic: license-file
